{
  "ComponentIndexes": {},
  "ControlUniqueGuids": {},
  "ControlUniqueIds": {
    "App": 1,
    "BrowseGallery1_1": 266,
    "BrowseGallery1_10": 505,
    "BrowseGallery1_11": 558,
    "BrowseGallery1_12": 371,
    "BrowseGallery1_13": 280,
    "BrowseGallery1_14": 161,
    "BrowseGallery1_2": 519,
    "BrowseGallery1_3": 572,
    "BrowseGallery1_4": 397,
    "BrowseGallery1_5": 294,
    "BrowseGallery1_6": 175,
    "BrowseGallery1_7": 452,
    "BrowseGallery1_8": 438,
    "BrowseGallery1_9": 252,
    "Budżet_DataCard1": 683,
    "Budżet_DataCard2": 190,
    "Budżet_DataCard3": 219,
    "Button1": 382,
    "Button1_1": 383,
    "Button1_2": 384,
    "Button1_3": 385,
    "Button1_4": 386,
    "Button1_5": 387,
    "Button1_6": 388,
    "Button2": 360,
    "Button2_1": 361,
    "Button2_3": 359,
    "Button3": 663,
    "Button3_1": 664,
    "Button3_10": 586,
    "Button3_11": 587,
    "Button3_12": 588,
    "Button3_13": 589,
    "Button3_2": 665,
    "Button3_3": 666,
    "Button3_4": 667,
    "Button3_5": 668,
    "Button3_6": 669,
    "Button3_7": 583,
    "Button3_8": 584,
    "Button3_9": 585,
    "CreateMenu": 377,
    "Data premiery_DataCard1": 693,
    "Data premiery_DataCard2": 196,
    "Data premiery_DataCard3": 229,
    "Data Rozpoczęcia_DataCard1": 316,
    "Data Rozpoczęcia_DataCard2": 534,
    "Data Rozpoczęcia_DataCard3": 52,
    "Data Urodzenia_DataCard1": 138,
    "Data Urodzenia_DataCard2": 476,
    "Data Urodzenia_DataCard5": 30,
    "Data Zatrudnienia_DataCard1": 143,
    "Data Zatrudnienia_DataCard2": 479,
    "Data Zatrudnienia_DataCard5": 35,
    "data_urodzenia_DataCard1": 755,
    "data_urodzenia_DataCard2": 421,
    "data_urodzenia_DataCard3": 644,
    "data_zatrudnienia_DataCard1": 760,
    "data_zatrudnienia_DataCard2": 424,
    "data_zatrudnienia_DataCard3": 649,
    "DataCardKey1": 532,
    "DataCardKey10": 471,
    "DataCardKey100": 226,
    "DataCardKey101": 231,
    "DataCardKey102": 236,
    "DataCardKey104": 241,
    "DataCardKey11": 477,
    "DataCardKey12": 120,
    "DataCardKey13": 125,
    "DataCardKey14": 145,
    "DataCardKey15": 150,
    "DataCardKey16": 130,
    "DataCardKey17": 140,
    "DataCardKey18": 135,
    "DataCardKey19": 474,
    "DataCardKey2": 535,
    "DataCardKey20": 713,
    "DataCardKey21": 808,
    "DataCardKey22": 318,
    "DataCardKey23": 323,
    "DataCardKey24": 331,
    "DataCardKey25": 336,
    "DataCardKey26": 341,
    "DataCardKey27": 465,
    "DataCardKey28": 779,
    "DataCardKey29": 784,
    "DataCardKey3": 538,
    "DataCardKey30": 789,
    "DataCardKey31": 794,
    "DataCardKey32": 799,
    "DataCardKey33": 597,
    "DataCardKey34": 737,
    "DataCardKey35": 742,
    "DataCardKey36": 747,
    "DataCardKey37": 752,
    "DataCardKey38": 757,
    "DataCardKey39": 762,
    "DataCardKey4": 542,
    "DataCardKey40": 767,
    "DataCardKey41": 600,
    "DataCardKey42": 725,
    "DataCardKey43": 604,
    "DataCardKey44": 680,
    "DataCardKey45": 685,
    "DataCardKey46": 690,
    "DataCardKey47": 695,
    "DataCardKey48": 700,
    "DataCardKey49": 609,
    "DataCardKey5": 547,
    "DataCardKey50": 614,
    "DataCardKey51": 410,
    "DataCardKey52": 413,
    "DataCardKey53": 416,
    "DataCardKey54": 419,
    "DataCardKey55": 32,
    "DataCardKey56": 37,
    "DataCardKey57": 12,
    "DataCardKey58": 17,
    "DataCardKey59": 27,
    "DataCardKey6": 803,
    "DataCardKey60": 22,
    "DataCardKey61": 422,
    "DataCardKey62": 425,
    "DataCardKey63": 428,
    "DataCardKey64": 307,
    "DataCardKey65": 188,
    "DataCardKey66": 191,
    "DataCardKey67": 194,
    "DataCardKey68": 197,
    "DataCardKey69": 201,
    "DataCardKey7": 468,
    "DataCardKey70": 42,
    "DataCardKey73": 205,
    "DataCardKey74": 353,
    "DataCardKey76": 54,
    "DataCardKey77": 59,
    "DataCardKey78": 67,
    "DataCardKey79": 72,
    "DataCardKey8": 480,
    "DataCardKey80": 77,
    "DataCardKey82": 89,
    "DataCardKey83": 94,
    "DataCardKey84": 99,
    "DataCardKey85": 104,
    "DataCardKey86": 109,
    "DataCardKey88": 626,
    "DataCardKey89": 631,
    "DataCardKey9": 483,
    "DataCardKey90": 636,
    "DataCardKey91": 641,
    "DataCardKey92": 646,
    "DataCardKey93": 651,
    "DataCardKey94": 656,
    "DataCardKey96": 494,
    "DataCardKey98": 216,
    "DataCardKey99": 221,
    "DataCardValue1": 533,
    "DataCardValue10": 472,
    "DataCardValue100": 237,
    "DataCardValue102": 242,
    "DataCardValue11": 478,
    "DataCardValue12": 121,
    "DataCardValue13": 126,
    "DataCardValue14": 146,
    "DataCardValue15": 151,
    "DataCardValue16": 131,
    "DataCardValue17": 141,
    "DataCardValue18": 136,
    "DataCardValue19": 475,
    "DataCardValue2": 536,
    "DataCardValue20": 714,
    "DataCardValue21": 809,
    "DataCardValue22": 319,
    "DataCardValue23": 332,
    "DataCardValue24": 337,
    "DataCardValue25": 342,
    "DataCardValue26": 466,
    "DataCardValue27": 780,
    "DataCardValue28": 785,
    "DataCardValue29": 790,
    "DataCardValue3": 539,
    "DataCardValue30": 795,
    "DataCardValue31": 800,
    "DataCardValue32": 598,
    "DataCardValue33": 738,
    "DataCardValue34": 743,
    "DataCardValue35": 748,
    "DataCardValue36": 753,
    "DataCardValue37": 758,
    "DataCardValue38": 763,
    "DataCardValue39": 768,
    "DataCardValue4": 543,
    "DataCardValue40": 601,
    "DataCardValue41": 726,
    "DataCardValue42": 605,
    "DataCardValue43": 681,
    "DataCardValue44": 686,
    "DataCardValue45": 691,
    "DataCardValue46": 696,
    "DataCardValue47": 701,
    "DataCardValue48": 610,
    "DataCardValue49": 615,
    "DataCardValue5": 548,
    "DataCardValue50": 411,
    "DataCardValue51": 414,
    "DataCardValue52": 417,
    "DataCardValue53": 420,
    "DataCardValue54": 33,
    "DataCardValue55": 38,
    "DataCardValue56": 13,
    "DataCardValue57": 18,
    "DataCardValue58": 28,
    "DataCardValue59": 23,
    "DataCardValue6": 804,
    "DataCardValue60": 423,
    "DataCardValue61": 426,
    "DataCardValue62": 429,
    "DataCardValue63": 308,
    "DataCardValue64": 189,
    "DataCardValue65": 192,
    "DataCardValue66": 195,
    "DataCardValue67": 198,
    "DataCardValue68": 202,
    "DataCardValue69": 43,
    "DataCardValue7": 469,
    "DataCardValue72": 206,
    "DataCardValue73": 354,
    "DataCardValue75": 55,
    "DataCardValue76": 68,
    "DataCardValue77": 73,
    "DataCardValue78": 78,
    "DataCardValue8": 481,
    "DataCardValue80": 90,
    "DataCardValue81": 95,
    "DataCardValue82": 100,
    "DataCardValue83": 105,
    "DataCardValue84": 110,
    "DataCardValue86": 627,
    "DataCardValue87": 632,
    "DataCardValue88": 637,
    "DataCardValue89": 642,
    "DataCardValue9": 484,
    "DataCardValue90": 647,
    "DataCardValue91": 652,
    "DataCardValue92": 657,
    "DataCardValue94": 495,
    "DataCardValue96": 217,
    "DataCardValue97": 222,
    "DataCardValue98": 227,
    "DataCardValue99": 232,
    "DateValue1": 324,
    "DateValue2": 60,
    "DisplayAndDeleteMenu": 579,
    "DisplayAndEditMenu": 659,
    "Dodaj film": 671,
    "Dodaj gatunek": 703,
    "Dodaj lokalizacje": 716,
    "Dodaj menadzera": 728,
    "Dodaj pracownika": 112,
    "Dodaj spotkanie": 309,
    "Dodaj zadanie": 770,
    "EditForm2": 117,
    "EditForm3": 710,
    "EditForm4": 315,
    "EditForm5": 776,
    "EditForm6": 734,
    "EditForm7": 722,
    "EditForm8": 677,
    "EditForm9": 9,
    "EditForm9_1": 350,
    "EditForm9_2": 51,
    "EditForm9_3": 86,
    "EditForm9_4": 623,
    "EditForm9_5": 491,
    "EditForm9_6": 213,
    "EdytujFilm": 207,
    "EdytujGatunek": 344,
    "EdytujLokalizacje": 485,
    "EdytujMenedzera": 617,
    "EdytujPracownika": 3,
    "EdytujSpotkanie": 45,
    "EdytujZadanie": 80,
    "email_DataCard1": 750,
    "email_DataCard2": 418,
    "email_DataCard3": 639,
    "ErrorMessage1": 544,
    "ErrorMessage10": 122,
    "ErrorMessage11": 127,
    "ErrorMessage12": 147,
    "ErrorMessage13": 152,
    "ErrorMessage14": 132,
    "ErrorMessage15": 142,
    "ErrorMessage16": 137,
    "ErrorMessage17": 14,
    "ErrorMessage18": 715,
    "ErrorMessage19": 19,
    "ErrorMessage2": 549,
    "ErrorMessage20": 320,
    "ErrorMessage21": 328,
    "ErrorMessage22": 333,
    "ErrorMessage23": 338,
    "ErrorMessage24": 343,
    "ErrorMessage25": 29,
    "ErrorMessage26": 781,
    "ErrorMessage27": 786,
    "ErrorMessage28": 791,
    "ErrorMessage29": 796,
    "ErrorMessage3": 606,
    "ErrorMessage30": 801,
    "ErrorMessage31": 24,
    "ErrorMessage32": 739,
    "ErrorMessage33": 744,
    "ErrorMessage34": 749,
    "ErrorMessage35": 754,
    "ErrorMessage36": 759,
    "ErrorMessage37": 764,
    "ErrorMessage38": 769,
    "ErrorMessage39": 355,
    "ErrorMessage4": 611,
    "ErrorMessage40": 727,
    "ErrorMessage41": 805,
    "ErrorMessage42": 682,
    "ErrorMessage43": 687,
    "ErrorMessage44": 692,
    "ErrorMessage45": 697,
    "ErrorMessage46": 702,
    "ErrorMessage47": 56,
    "ErrorMessage48": 64,
    "ErrorMessage49": 69,
    "ErrorMessage5": 616,
    "ErrorMessage50": 74,
    "ErrorMessage51": 79,
    "ErrorMessage52": 810,
    "ErrorMessage53": 91,
    "ErrorMessage54": 96,
    "ErrorMessage55": 101,
    "ErrorMessage56": 106,
    "ErrorMessage57": 111,
    "ErrorMessage59": 628,
    "ErrorMessage6": 203,
    "ErrorMessage60": 633,
    "ErrorMessage61": 638,
    "ErrorMessage62": 643,
    "ErrorMessage63": 648,
    "ErrorMessage64": 653,
    "ErrorMessage65": 658,
    "ErrorMessage67": 496,
    "ErrorMessage69": 218,
    "ErrorMessage7": 44,
    "ErrorMessage70": 223,
    "ErrorMessage71": 228,
    "ErrorMessage72": 233,
    "ErrorMessage73": 238,
    "ErrorMessage75": 243,
    "ErrorMessage8": 34,
    "ErrorMessage9": 39,
    "Film_DataCard1": 540,
    "Film_DataCard2": 612,
    "Film_DataCard3": 334,
    "Film_DataCard4": 797,
    "Film_DataCard5": 70,
    "Film_DataCard6": 107,
    "Filmy_usun": 153,
    "Filmy_wyswietl": 167,
    "Filmy_wyswietl_szczegoly": 182,
    "FormViewer2_1": 530,
    "FormViewer2_2": 463,
    "FormViewer2_3": 595,
    "FormViewer2_4": 408,
    "FormViewer2_5": 305,
    "FormViewer2_6": 186,
    "galleryTemplate3_1": 267,
    "galleryTemplate3_10": 506,
    "galleryTemplate3_11": 559,
    "galleryTemplate3_12": 372,
    "galleryTemplate3_13": 281,
    "galleryTemplate3_14": 162,
    "galleryTemplate3_2": 520,
    "galleryTemplate3_3": 573,
    "galleryTemplate3_4": 398,
    "galleryTemplate3_5": 295,
    "galleryTemplate3_6": 176,
    "galleryTemplate3_7": 453,
    "galleryTemplate3_8": 439,
    "galleryTemplate3_9": 253,
    "Gatunek_DataCard1": 698,
    "Gatunek_DataCard2": 199,
    "Gatunek_DataCard3": 234,
    "Gatunki_usun": 244,
    "Gatunki_wyswietl": 258,
    "Godzina Rozpoczęcia_DataCard1": 321,
    "Godzina Rozpoczęcia_DataCard2": 537,
    "Godzina Rozpoczęcia_DataCard3": 57,
    "HourValue1": 325,
    "HourValue2": 61,
    "Icon1": 116,
    "Icon1_1": 709,
    "Icon1_10": 8,
    "Icon1_11": 349,
    "Icon1_12": 263,
    "Icon1_13": 516,
    "Icon1_14": 569,
    "Icon1_15": 394,
    "Icon1_16": 291,
    "Icon1_17": 172,
    "Icon1_18": 529,
    "Icon1_19": 449,
    "Icon1_2": 314,
    "Icon1_20": 462,
    "Icon1_21": 594,
    "Icon1_22": 407,
    "Icon1_23": 304,
    "Icon1_24": 185,
    "Icon1_25": 50,
    "Icon1_26": 85,
    "Icon1_27": 622,
    "Icon1_28": 490,
    "Icon1_29": 212,
    "Icon1_3": 775,
    "Icon1_30": 435,
    "Icon1_31": 249,
    "Icon1_32": 502,
    "Icon1_33": 555,
    "Icon1_34": 368,
    "Icon1_35": 277,
    "Icon1_36": 158,
    "Icon1_4": 733,
    "Icon1_5": 721,
    "Icon1_6": 676,
    "Icon1_7": 381,
    "Icon1_8": 662,
    "Icon1_9": 582,
    "Icon10": 163,
    "Icon2": 440,
    "Icon4": 254,
    "Icon4_1": 268,
    "Icon4_2": 521,
    "Icon4_3": 574,
    "Icon4_4": 399,
    "Icon4_5": 296,
    "Icon4_6": 177,
    "Icon4_7": 454,
    "Icon5": 507,
    "Icon6": 560,
    "Icon8": 373,
    "Icon9": 282,
    "IconAccept2": 115,
    "IconAccept3": 708,
    "IconAccept4": 313,
    "IconAccept5": 774,
    "IconAccept6": 732,
    "IconAccept7": 720,
    "IconAccept8": 675,
    "IconAccept9": 7,
    "IconAccept9_1": 348,
    "IconAccept9_2": 49,
    "IconAccept9_3": 84,
    "IconAccept9_4": 621,
    "IconAccept9_5": 489,
    "IconAccept9_6": 211,
    "IconCancel3": 705,
    "IconCancel4": 310,
    "IconCancel5": 771,
    "IconCancel6": 729,
    "IconCancel7": 717,
    "IconCancel8": 672,
    "IconRefresh1_1": 261,
    "IconRefresh1_10": 500,
    "IconRefresh1_11": 553,
    "IconRefresh1_12": 366,
    "IconRefresh1_13": 275,
    "IconRefresh1_14": 156,
    "IconRefresh1_2": 514,
    "IconRefresh1_3": 567,
    "IconRefresh1_4": 392,
    "IconRefresh1_5": 289,
    "IconRefresh1_6": 170,
    "IconRefresh1_7": 447,
    "IconRefresh1_8": 433,
    "IconRefresh1_9": 247,
    "IconSortUpDown1_1": 262,
    "IconSortUpDown1_10": 501,
    "IconSortUpDown1_11": 554,
    "IconSortUpDown1_12": 367,
    "IconSortUpDown1_13": 276,
    "IconSortUpDown1_14": 157,
    "IconSortUpDown1_2": 515,
    "IconSortUpDown1_3": 568,
    "IconSortUpDown1_4": 393,
    "IconSortUpDown1_5": 290,
    "IconSortUpDown1_6": 171,
    "IconSortUpDown1_7": 448,
    "IconSortUpDown1_8": 434,
    "IconSortUpDown1_9": 248,
    "Image1": 362,
    "imie _DataCard1": 735,
    "imie _DataCard2": 409,
    "imie _DataCard3": 624,
    "Imię_DataCard1": 118,
    "Imię_DataCard2": 464,
    "Imię_DataCard5": 10,
    "Label1": 379,
    "Label2": 358,
    "Label3": 661,
    "Label3_1": 581,
    "Label4": 670,
    "Label4_1": 590,
    "Label5_1": 528,
    "Label5_2": 461,
    "Label5_3": 593,
    "Label5_4": 406,
    "Label5_5": 303,
    "Label5_6": 184,
    "Latitiude_DataCard1": 802,
    "Latitiude1": 814,
    "LblAppName1": 380,
    "LblAppName10": 719,
    "LblAppName11": 674,
    "LblAppName2_1": 260,
    "LblAppName2_10": 499,
    "LblAppName2_11": 552,
    "LblAppName2_12": 365,
    "LblAppName2_13": 274,
    "LblAppName2_14": 155,
    "LblAppName2_2": 513,
    "LblAppName2_3": 566,
    "LblAppName2_4": 391,
    "LblAppName2_5": 288,
    "LblAppName2_6": 169,
    "LblAppName2_7": 446,
    "LblAppName2_8": 432,
    "LblAppName2_9": 246,
    "LblAppName4": 6,
    "LblAppName4_1": 347,
    "LblAppName4_2": 48,
    "LblAppName4_3": 83,
    "LblAppName4_4": 620,
    "LblAppName4_5": 488,
    "LblAppName4_6": 210,
    "LblAppName5": 114,
    "LblAppName6": 707,
    "LblAppName7": 312,
    "LblAppName8": 773,
    "LblAppName9": 731,
    "Lokalizacja_DataCard1": 339,
    "Lokalizacja_DataCard2": 723,
    "Lokalizacja_DataCard3": 545,
    "Lokalizacja_DataCard4": 306,
    "Lokalizacja_DataCard5": 75,
    "Lokalizacja_DataCard6": 492,
    "Lokalizacja1": 813,
    "Lokalizacje_usun": 272,
    "Lokalizacje_wyswietl": 286,
    "Lokalizacje_wyswietl_szczegoly": 301,
    "Longitude_DataCard1": 807,
    "Longitude1": 815,
    "MainMenu": 356,
    "Map1": 812,
    "Menedzerowie_usun": 363,
    "Menedzerowie_wyswietl": 389,
    "Menedzerowie_wyswietl_szczegoly": 404,
    "Menedżer_DataCard1": 607,
    "Menedżer_DataCard2": 102,
    "Menedżer_DataCard3": 792,
    "MinuteValue1": 327,
    "MinuteValue2": 63,
    "Nazwa (Title)_DataCard1": 678,
    "Nazwa (Title)_DataCard2": 187,
    "Nazwa (Title)_DataCard3": 214,
    "Nazwa Gatunku_DataCard1": 711,
    "Nazwa Gatunku_DataCard2": 351,
    "Nazwa_DataCard1": 531,
    "nazwisko _DataCard1": 740,
    "nazwisko _DataCard2": 412,
    "nazwisko _DataCard3": 629,
    "Nazwisko_DataCard1": 123,
    "Nazwisko_DataCard2": 467,
    "Nazwisko_DataCard5": 15,
    "NextArrow6_2": 522,
    "NextArrow6_3": 575,
    "NextArrow6_4": 400,
    "NextArrow6_5": 297,
    "NextArrow6_6": 178,
    "NextArrow6_7": 455,
    "Numer telefonu_DataCard1": 133,
    "Numer telefonu_DataCard2": 473,
    "Numer telefonu_DataCard5": 25,
    "numer_telefonu_DataCard1": 745,
    "numer_telefonu_DataCard2": 415,
    "numer_telefonu_DataCard3": 634,
    "Oceny użytkownika_DataCard1": 204,
    "Oceny użytkownika_DataCard2": 239,
    "Ograniczenie wiekowe_DataCard1": 688,
    "Ograniczenie wiekowe_DataCard2": 193,
    "Ograniczenie wiekowe_DataCard3": 224,
    "Opis zadania_DataCard1": 596,
    "Opis zadania_DataCard2": 87,
    "Opis zadania_DataCard3": 777,
    "Opis_DataCard1": 329,
    "Opis_DataCard2": 65,
    "Pracownicy_usun": 430,
    "Pracownicy_wyswietl": 444,
    "Pracownicy_wyswietl_szczegoly": 459,
    "Pracownik_DataCard1": 602,
    "Pracownik_DataCard2": 97,
    "Pracownik_DataCard3": 787,
    "Rectangle12_1": 271,
    "Rectangle12_10": 510,
    "Rectangle12_11": 563,
    "Rectangle12_12": 376,
    "Rectangle12_13": 285,
    "Rectangle12_14": 166,
    "Rectangle12_2": 525,
    "Rectangle12_3": 578,
    "Rectangle12_4": 403,
    "Rectangle12_5": 300,
    "Rectangle12_6": 181,
    "Rectangle12_7": 458,
    "Rectangle12_8": 443,
    "Rectangle12_9": 257,
    "RectQuickActionBar4": 5,
    "RectQuickActionBar4_1": 346,
    "RectQuickActionBar4_2": 47,
    "RectQuickActionBar4_3": 82,
    "RectQuickActionBar4_4": 619,
    "RectQuickActionBar4_5": 487,
    "RectQuickActionBar4_6": 209,
    "RectQuickActionBar5_1": 357,
    "RectQuickActionBar5_10": 168,
    "RectQuickActionBar5_11": 527,
    "RectQuickActionBar5_12": 445,
    "RectQuickActionBar5_13": 460,
    "RectQuickActionBar5_14": 592,
    "RectQuickActionBar5_15": 405,
    "RectQuickActionBar5_16": 302,
    "RectQuickActionBar5_17": 183,
    "RectQuickActionBar5_18": 4,
    "RectQuickActionBar5_19": 345,
    "RectQuickActionBar5_2": 660,
    "RectQuickActionBar5_20": 46,
    "RectQuickActionBar5_21": 81,
    "RectQuickActionBar5_22": 618,
    "RectQuickActionBar5_23": 486,
    "RectQuickActionBar5_24": 208,
    "RectQuickActionBar5_25": 378,
    "RectQuickActionBar5_26": 113,
    "RectQuickActionBar5_27": 704,
    "RectQuickActionBar5_28": 311,
    "RectQuickActionBar5_29": 772,
    "RectQuickActionBar5_3": 580,
    "RectQuickActionBar5_30": 730,
    "RectQuickActionBar5_31": 718,
    "RectQuickActionBar5_32": 673,
    "RectQuickActionBar5_33": 431,
    "RectQuickActionBar5_34": 245,
    "RectQuickActionBar5_35": 498,
    "RectQuickActionBar5_36": 551,
    "RectQuickActionBar5_37": 364,
    "RectQuickActionBar5_38": 273,
    "RectQuickActionBar5_39": 154,
    "RectQuickActionBar5_5": 259,
    "RectQuickActionBar5_6": 512,
    "RectQuickActionBar5_7": 565,
    "RectQuickActionBar5_8": 390,
    "RectQuickActionBar5_9": 287,
    "RectQuickActionBar6": 706,
    "Rola _DataCard1": 128,
    "Rola _DataCard2": 470,
    "Rola _DataCard5": 20,
    "SearchIcon1_1": 265,
    "SearchIcon1_10": 504,
    "SearchIcon1_11": 557,
    "SearchIcon1_12": 370,
    "SearchIcon1_13": 279,
    "SearchIcon1_14": 160,
    "SearchIcon1_2": 518,
    "SearchIcon1_3": 571,
    "SearchIcon1_4": 396,
    "SearchIcon1_5": 293,
    "SearchIcon1_6": 174,
    "SearchIcon1_7": 451,
    "SearchIcon1_8": 437,
    "SearchIcon1_9": 251,
    "Separator1": 62,
    "Separator3": 326,
    "Separator7_1": 270,
    "Separator7_10": 509,
    "Separator7_11": 562,
    "Separator7_12": 375,
    "Separator7_13": 284,
    "Separator7_14": 165,
    "Separator7_2": 524,
    "Separator7_3": 577,
    "Separator7_4": 402,
    "Separator7_5": 299,
    "Separator7_6": 180,
    "Separator7_7": 457,
    "Separator7_8": 442,
    "Separator7_9": 256,
    "Spotkania_usun": 497,
    "Spotkania_wyswietl": 511,
    "Spotkania_wyswietl_szczegoly": 526,
    "StarVisible1": 541,
    "StarVisible10": 119,
    "StarVisible11": 124,
    "StarVisible12": 144,
    "StarVisible13": 149,
    "StarVisible14": 129,
    "StarVisible15": 139,
    "StarVisible16": 134,
    "StarVisible17": 11,
    "StarVisible18": 712,
    "StarVisible19": 16,
    "StarVisible2": 546,
    "StarVisible20": 317,
    "StarVisible21": 322,
    "StarVisible22": 330,
    "StarVisible23": 335,
    "StarVisible24": 340,
    "StarVisible25": 26,
    "StarVisible26": 778,
    "StarVisible27": 783,
    "StarVisible28": 788,
    "StarVisible29": 793,
    "StarVisible3": 603,
    "StarVisible30": 798,
    "StarVisible31": 21,
    "StarVisible32": 736,
    "StarVisible33": 741,
    "StarVisible34": 746,
    "StarVisible35": 751,
    "StarVisible36": 756,
    "StarVisible37": 761,
    "StarVisible38": 766,
    "StarVisible39": 352,
    "StarVisible4": 608,
    "StarVisible40": 724,
    "StarVisible41": 806,
    "StarVisible42": 679,
    "StarVisible43": 684,
    "StarVisible44": 689,
    "StarVisible45": 694,
    "StarVisible46": 699,
    "StarVisible47": 53,
    "StarVisible48": 58,
    "StarVisible49": 66,
    "StarVisible5": 613,
    "StarVisible50": 71,
    "StarVisible51": 76,
    "StarVisible52": 811,
    "StarVisible53": 88,
    "StarVisible54": 93,
    "StarVisible55": 98,
    "StarVisible56": 103,
    "StarVisible57": 108,
    "StarVisible59": 625,
    "StarVisible6": 200,
    "StarVisible60": 630,
    "StarVisible61": 635,
    "StarVisible62": 640,
    "StarVisible63": 645,
    "StarVisible64": 650,
    "StarVisible65": 655,
    "StarVisible67": 493,
    "StarVisible69": 215,
    "StarVisible7": 41,
    "StarVisible70": 220,
    "StarVisible71": 225,
    "StarVisible72": 230,
    "StarVisible73": 235,
    "StarVisible75": 240,
    "StarVisible8": 31,
    "StarVisible9": 36,
    "Termin wykonania_DataCard1": 599,
    "Termin wykonania_DataCard2": 92,
    "Termin wykonania_DataCard3": 782,
    "TextSearchBox1_1": 264,
    "TextSearchBox1_10": 503,
    "TextSearchBox1_11": 556,
    "TextSearchBox1_12": 369,
    "TextSearchBox1_13": 278,
    "TextSearchBox1_14": 159,
    "TextSearchBox1_2": 517,
    "TextSearchBox1_3": 570,
    "TextSearchBox1_4": 395,
    "TextSearchBox1_5": 292,
    "TextSearchBox1_6": 173,
    "TextSearchBox1_7": 450,
    "TextSearchBox1_8": 436,
    "TextSearchBox1_9": 250,
    "Title6_1": 269,
    "Title6_10": 508,
    "Title6_11": 561,
    "Title6_12": 374,
    "Title6_13": 283,
    "Title6_14": 164,
    "Title6_2": 523,
    "Title6_3": 576,
    "Title6_4": 401,
    "Title6_5": 298,
    "Title6_6": 179,
    "Title6_7": 456,
    "Title6_8": 441,
    "Title6_9": 255,
    "Toggle_satelite": 817,
    "wynagrodzenie _DataCard1": 765,
    "wynagrodzenie _DataCard2": 427,
    "wynagrodzenie _DataCard3": 654,
    "Wynagrodzenie_DataCard1": 148,
    "Wynagrodzenie_DataCard2": 482,
    "Wynagrodzenie_DataCard3": 40,
    "Zadania_usun": 550,
    "Zadania_wyswietl": 564,
    "Zadania_wyswietl_szczegoly": 591,
    "Załączniki1": 816
  },
  "FunctionParamsInvariantScripts": {},
  "FunctionParamsInvariantScriptsOnInstances": {},
  "HeaderLastSavedDateTimeUTC": "11/07/2022 19:19:27",
  "IsLegacyComponentAllowGlobalScopeCase": false,
  "LocalConnectionIDReferences": {
    "2c465da7-916c-4257-a26d-737ff2848444": "\"/providers/microsoft.powerapps/apis/shared_sharepointonline/connections/ee9b9c6ffe52438599a3eca0a127c4c1\"",
    "84640625-e45d-4369-bf82-9705287d10de": "\"/providers/microsoft.powerapps/apis/shared_microsoftspatialservices/connections/503c4f0e9bf844d3961f800484491025\""
  },
  "LocalDatabaseReferencesAsEmpty": false,
  "LocalResourceFileNames": {
    "Filmoplaner": "0001.png",
    "filmoplanerbackground": "0002.png"
  },
  "LocalResourceRootPaths": {
    "Filmoplaner": "https://docserverpwaprodweu.blob.core.windows.net/f3102d84-e4b6-409d-890a-260907a0b4ec-1/resource/Assets0Images00001.png?sv=2017-04-17&sr=b&sig=bAhFCY%2BHbre62xYD%2ByBuNX4Bul5KxhXefznRNTmeKpg%3D&spr=https&se=2022-11-08T19%3A05%3A28Z&sp=r",
    "filmoplanerbackground": "https://docserverpwaprodweu.blob.core.windows.net/f3102d84-e4b6-409d-890a-260907a0b4ec-1/resource/Assets0Images00002.png?sv=2017-04-17&sr=b&sig=oQMUAVaAjQrv%2FF4YeoGxa%2BOr7BDx1nNdN7ef3XRZzVU%3D&spr=https&se=2022-11-08T19%3A05%3A28Z&sp=r"
  },
  "OrderComponentMetadata": {},
  "OrderComponentTemplate": {},
  "OrderDataSource": {
    "ComboBoxSample": 1,
    "CustomGallerySample": 2,
    "DropDownSample": 3,
    "Film_1": 4,
    "Gatunki filmów": 5,
    "Gatunki filmów_1": 6,
    "Lokalizacja": 7,
    "Menedżer": 8,
    "Pracownik": 9,
    "Pracownik_1": 10,
    "Pracownik_2": 11,
    "Skład zespołu": 12,
    "SpatialServices": 0,
    "Spotkanie": 13,
    "Zadanie": 14,
    "Zadanie_1": 15
  },
  "OrderGroupControls": {},
  "OrderPcfTemplate": {
    "Map": 0
  },
  "OrderTemplate": {},
  "OrderXMLTemplate": {
    "button": 12,
    "combobox": 7,
    "datepicker": 5,
    "dropdown": 6,
    "form": 3,
    "formViewer": 9,
    "gallery": 8,
    "icon": 2,
    "image": 13,
    "label": 1,
    "pcfDataField": 10,
    "rectangle": 0,
    "text": 4,
    "toggleSwitch": 11
  },
  "PublishOrderIndices": {
    "App": 0,
    "BrowseGallery1_1": 51,
    "BrowseGallery1_10": 91,
    "BrowseGallery1_11": 118,
    "BrowseGallery1_12": 145,
    "BrowseGallery1_13": 178,
    "BrowseGallery1_14": 205,
    "BrowseGallery1_2": 77,
    "BrowseGallery1_3": 104,
    "BrowseGallery1_4": 131,
    "BrowseGallery1_5": 158,
    "BrowseGallery1_6": 191,
    "BrowseGallery1_7": 24,
    "BrowseGallery1_8": 38,
    "BrowseGallery1_9": 64,
    "Budżet_DataCard1": 746,
    "Budżet_DataCard2": 323,
    "Budżet_DataCard3": 530,
    "Button1": 559,
    "Button1_1": 560,
    "Button1_2": 561,
    "Button1_3": 562,
    "Button1_4": 563,
    "Button1_5": 564,
    "Button1_6": 565,
    "Button2": 3,
    "Button2_1": 4,
    "Button2_3": 2,
    "Button3": 9,
    "Button3_1": 10,
    "Button3_10": 772,
    "Button3_11": 773,
    "Button3_12": 774,
    "Button3_13": 775,
    "Button3_2": 11,
    "Button3_3": 12,
    "Button3_4": 13,
    "Button3_5": 14,
    "Button3_6": 15,
    "Button3_7": 769,
    "Button3_8": 770,
    "Button3_9": 771,
    "CreateMenu": 2,
    "Data premiery_DataCard1": 756,
    "Data premiery_DataCard2": 329,
    "Data premiery_DataCard3": 540,
    "Data Rozpoczęcia_DataCard1": 624,
    "Data Rozpoczęcia_DataCard2": 243,
    "Data Rozpoczęcia_DataCard3": 398,
    "Data Urodzenia_DataCard1": 591,
    "Data Urodzenia_DataCard2": 227,
    "Data Urodzenia_DataCard5": 366,
    "Data Zatrudnienia_DataCard1": 596,
    "Data Zatrudnienia_DataCard2": 230,
    "Data Zatrudnienia_DataCard5": 371,
    "data_urodzenia_DataCard1": 709,
    "data_urodzenia_DataCard2": 300,
    "data_urodzenia_DataCard3": 483,
    "data_zatrudnienia_DataCard1": 714,
    "data_zatrudnienia_DataCard2": 303,
    "data_zatrudnienia_DataCard3": 488,
    "DataCardKey1": 241,
    "DataCardKey10": 222,
    "DataCardKey100": 537,
    "DataCardKey101": 542,
    "DataCardKey102": 547,
    "DataCardKey104": 552,
    "DataCardKey11": 228,
    "DataCardKey12": 573,
    "DataCardKey13": 578,
    "DataCardKey14": 598,
    "DataCardKey15": 603,
    "DataCardKey16": 583,
    "DataCardKey17": 593,
    "DataCardKey18": 588,
    "DataCardKey19": 225,
    "DataCardKey2": 244,
    "DataCardKey20": 615,
    "DataCardKey21": 516,
    "DataCardKey22": 626,
    "DataCardKey23": 631,
    "DataCardKey24": 639,
    "DataCardKey25": 644,
    "DataCardKey26": 649,
    "DataCardKey27": 216,
    "DataCardKey28": 660,
    "DataCardKey29": 665,
    "DataCardKey3": 247,
    "DataCardKey30": 670,
    "DataCardKey31": 675,
    "DataCardKey32": 680,
    "DataCardKey33": 264,
    "DataCardKey34": 691,
    "DataCardKey35": 696,
    "DataCardKey36": 701,
    "DataCardKey37": 706,
    "DataCardKey38": 711,
    "DataCardKey39": 716,
    "DataCardKey4": 251,
    "DataCardKey40": 721,
    "DataCardKey41": 267,
    "DataCardKey42": 732,
    "DataCardKey43": 271,
    "DataCardKey44": 743,
    "DataCardKey45": 748,
    "DataCardKey46": 753,
    "DataCardKey47": 758,
    "DataCardKey48": 763,
    "DataCardKey49": 276,
    "DataCardKey5": 256,
    "DataCardKey50": 281,
    "DataCardKey51": 289,
    "DataCardKey52": 292,
    "DataCardKey53": 295,
    "DataCardKey54": 298,
    "DataCardKey55": 368,
    "DataCardKey56": 373,
    "DataCardKey57": 348,
    "DataCardKey58": 353,
    "DataCardKey59": 363,
    "DataCardKey6": 511,
    "DataCardKey60": 358,
    "DataCardKey61": 301,
    "DataCardKey62": 304,
    "DataCardKey63": 307,
    "DataCardKey64": 314,
    "DataCardKey65": 321,
    "DataCardKey66": 324,
    "DataCardKey67": 327,
    "DataCardKey68": 330,
    "DataCardKey69": 334,
    "DataCardKey7": 219,
    "DataCardKey70": 378,
    "DataCardKey73": 338,
    "DataCardKey74": 389,
    "DataCardKey76": 400,
    "DataCardKey77": 405,
    "DataCardKey78": 413,
    "DataCardKey79": 418,
    "DataCardKey8": 231,
    "DataCardKey80": 423,
    "DataCardKey82": 434,
    "DataCardKey83": 439,
    "DataCardKey84": 444,
    "DataCardKey85": 449,
    "DataCardKey86": 454,
    "DataCardKey88": 465,
    "DataCardKey89": 470,
    "DataCardKey9": 234,
    "DataCardKey90": 475,
    "DataCardKey91": 480,
    "DataCardKey92": 485,
    "DataCardKey93": 490,
    "DataCardKey94": 495,
    "DataCardKey96": 506,
    "DataCardKey98": 527,
    "DataCardKey99": 532,
    "DataCardValue1": 242,
    "DataCardValue10": 223,
    "DataCardValue100": 548,
    "DataCardValue102": 553,
    "DataCardValue11": 229,
    "DataCardValue12": 574,
    "DataCardValue13": 579,
    "DataCardValue14": 599,
    "DataCardValue15": 604,
    "DataCardValue16": 584,
    "DataCardValue17": 594,
    "DataCardValue18": 589,
    "DataCardValue19": 226,
    "DataCardValue2": 245,
    "DataCardValue20": 616,
    "DataCardValue21": 517,
    "DataCardValue22": 627,
    "DataCardValue23": 640,
    "DataCardValue24": 645,
    "DataCardValue25": 650,
    "DataCardValue26": 217,
    "DataCardValue27": 661,
    "DataCardValue28": 666,
    "DataCardValue29": 671,
    "DataCardValue3": 248,
    "DataCardValue30": 676,
    "DataCardValue31": 681,
    "DataCardValue32": 265,
    "DataCardValue33": 692,
    "DataCardValue34": 697,
    "DataCardValue35": 702,
    "DataCardValue36": 707,
    "DataCardValue37": 712,
    "DataCardValue38": 717,
    "DataCardValue39": 722,
    "DataCardValue4": 252,
    "DataCardValue40": 268,
    "DataCardValue41": 733,
    "DataCardValue42": 272,
    "DataCardValue43": 744,
    "DataCardValue44": 749,
    "DataCardValue45": 754,
    "DataCardValue46": 759,
    "DataCardValue47": 764,
    "DataCardValue48": 277,
    "DataCardValue49": 282,
    "DataCardValue5": 257,
    "DataCardValue50": 290,
    "DataCardValue51": 293,
    "DataCardValue52": 296,
    "DataCardValue53": 299,
    "DataCardValue54": 369,
    "DataCardValue55": 374,
    "DataCardValue56": 349,
    "DataCardValue57": 354,
    "DataCardValue58": 364,
    "DataCardValue59": 359,
    "DataCardValue6": 512,
    "DataCardValue60": 302,
    "DataCardValue61": 305,
    "DataCardValue62": 308,
    "DataCardValue63": 315,
    "DataCardValue64": 322,
    "DataCardValue65": 325,
    "DataCardValue66": 328,
    "DataCardValue67": 331,
    "DataCardValue68": 335,
    "DataCardValue69": 379,
    "DataCardValue7": 220,
    "DataCardValue72": 339,
    "DataCardValue73": 390,
    "DataCardValue75": 401,
    "DataCardValue76": 414,
    "DataCardValue77": 419,
    "DataCardValue78": 424,
    "DataCardValue8": 232,
    "DataCardValue80": 435,
    "DataCardValue81": 440,
    "DataCardValue82": 445,
    "DataCardValue83": 450,
    "DataCardValue84": 455,
    "DataCardValue86": 466,
    "DataCardValue87": 471,
    "DataCardValue88": 476,
    "DataCardValue89": 481,
    "DataCardValue9": 235,
    "DataCardValue90": 486,
    "DataCardValue91": 491,
    "DataCardValue92": 496,
    "DataCardValue94": 507,
    "DataCardValue96": 528,
    "DataCardValue97": 533,
    "DataCardValue98": 538,
    "DataCardValue99": 543,
    "DateValue1": 632,
    "DateValue2": 406,
    "DisplayAndDeleteMenu": 14,
    "DisplayAndEditMenu": 26,
    "Dodaj film": 38,
    "Dodaj gatunek": 70,
    "Dodaj lokalizacje": 83,
    "Dodaj menadzera": 95,
    "Dodaj pracownika": 137,
    "Dodaj spotkanie": 178,
    "Dodaj zadanie": 213,
    "EditForm2": 570,
    "EditForm3": 612,
    "EditForm4": 623,
    "EditForm5": 657,
    "EditForm6": 688,
    "EditForm7": 729,
    "EditForm8": 740,
    "EditForm9": 345,
    "EditForm9_1": 386,
    "EditForm9_2": 397,
    "EditForm9_3": 431,
    "EditForm9_4": 462,
    "EditForm9_5": 503,
    "EditForm9_6": 524,
    "EdytujFilm": 245,
    "EdytujGatunek": 282,
    "EdytujLokalizacje": 294,
    "EdytujMenedzera": 306,
    "EdytujPracownika": 348,
    "EdytujSpotkanie": 390,
    "EdytujZadanie": 425,
    "email_DataCard1": 704,
    "email_DataCard2": 297,
    "email_DataCard3": 478,
    "ErrorMessage1": 253,
    "ErrorMessage10": 575,
    "ErrorMessage11": 580,
    "ErrorMessage12": 600,
    "ErrorMessage13": 605,
    "ErrorMessage14": 585,
    "ErrorMessage15": 595,
    "ErrorMessage16": 590,
    "ErrorMessage17": 350,
    "ErrorMessage18": 617,
    "ErrorMessage19": 355,
    "ErrorMessage2": 258,
    "ErrorMessage20": 628,
    "ErrorMessage21": 636,
    "ErrorMessage22": 641,
    "ErrorMessage23": 646,
    "ErrorMessage24": 651,
    "ErrorMessage25": 365,
    "ErrorMessage26": 662,
    "ErrorMessage27": 667,
    "ErrorMessage28": 672,
    "ErrorMessage29": 677,
    "ErrorMessage3": 273,
    "ErrorMessage30": 682,
    "ErrorMessage31": 360,
    "ErrorMessage32": 693,
    "ErrorMessage33": 698,
    "ErrorMessage34": 703,
    "ErrorMessage35": 708,
    "ErrorMessage36": 713,
    "ErrorMessage37": 718,
    "ErrorMessage38": 723,
    "ErrorMessage39": 391,
    "ErrorMessage4": 278,
    "ErrorMessage40": 734,
    "ErrorMessage41": 513,
    "ErrorMessage42": 745,
    "ErrorMessage43": 750,
    "ErrorMessage44": 755,
    "ErrorMessage45": 760,
    "ErrorMessage46": 765,
    "ErrorMessage47": 402,
    "ErrorMessage48": 410,
    "ErrorMessage49": 415,
    "ErrorMessage5": 283,
    "ErrorMessage50": 420,
    "ErrorMessage51": 425,
    "ErrorMessage52": 518,
    "ErrorMessage53": 436,
    "ErrorMessage54": 441,
    "ErrorMessage55": 446,
    "ErrorMessage56": 451,
    "ErrorMessage57": 456,
    "ErrorMessage59": 467,
    "ErrorMessage6": 336,
    "ErrorMessage60": 472,
    "ErrorMessage61": 477,
    "ErrorMessage62": 482,
    "ErrorMessage63": 487,
    "ErrorMessage64": 492,
    "ErrorMessage65": 497,
    "ErrorMessage67": 508,
    "ErrorMessage69": 529,
    "ErrorMessage7": 380,
    "ErrorMessage70": 534,
    "ErrorMessage71": 539,
    "ErrorMessage72": 544,
    "ErrorMessage73": 549,
    "ErrorMessage75": 554,
    "ErrorMessage8": 370,
    "ErrorMessage9": 375,
    "Film_DataCard1": 249,
    "Film_DataCard2": 279,
    "Film_DataCard3": 642,
    "Film_DataCard4": 678,
    "Film_DataCard5": 416,
    "Film_DataCard6": 452,
    "Filmy_usun": 457,
    "Filmy_wyswietl": 471,
    "Filmy_wyswietl_szczegoly": 486,
    "FormViewer2_1": 239,
    "FormViewer2_2": 214,
    "FormViewer2_3": 262,
    "FormViewer2_4": 287,
    "FormViewer2_5": 312,
    "FormViewer2_6": 319,
    "galleryTemplate3_1": 52,
    "galleryTemplate3_10": 92,
    "galleryTemplate3_11": 119,
    "galleryTemplate3_12": 146,
    "galleryTemplate3_13": 179,
    "galleryTemplate3_14": 206,
    "galleryTemplate3_2": 78,
    "galleryTemplate3_3": 105,
    "galleryTemplate3_4": 132,
    "galleryTemplate3_5": 159,
    "galleryTemplate3_6": 192,
    "galleryTemplate3_7": 25,
    "galleryTemplate3_8": 39,
    "galleryTemplate3_9": 65,
    "Gatunek_DataCard1": 761,
    "Gatunek_DataCard2": 332,
    "Gatunek_DataCard3": 545,
    "Gatunki_usun": 511,
    "Gatunki_wyswietl": 525,
    "Godzina Rozpoczęcia_DataCard1": 629,
    "Godzina Rozpoczęcia_DataCard2": 246,
    "Godzina Rozpoczęcia_DataCard3": 403,
    "HourValue1": 633,
    "HourValue2": 407,
    "Icon1": 569,
    "Icon1_1": 611,
    "Icon1_10": 344,
    "Icon1_11": 385,
    "Icon1_12": 48,
    "Icon1_13": 74,
    "Icon1_14": 101,
    "Icon1_15": 128,
    "Icon1_16": 155,
    "Icon1_17": 188,
    "Icon1_18": 238,
    "Icon1_19": 21,
    "Icon1_2": 622,
    "Icon1_20": 213,
    "Icon1_21": 261,
    "Icon1_22": 286,
    "Icon1_23": 311,
    "Icon1_24": 318,
    "Icon1_25": 396,
    "Icon1_26": 430,
    "Icon1_27": 461,
    "Icon1_28": 502,
    "Icon1_29": 523,
    "Icon1_3": 656,
    "Icon1_30": 35,
    "Icon1_31": 61,
    "Icon1_32": 88,
    "Icon1_33": 115,
    "Icon1_34": 142,
    "Icon1_35": 175,
    "Icon1_36": 202,
    "Icon1_4": 687,
    "Icon1_5": 728,
    "Icon1_6": 739,
    "Icon1_7": 558,
    "Icon1_8": 8,
    "Icon1_9": 768,
    "Icon10": 207,
    "Icon2": 40,
    "Icon4": 66,
    "Icon4_1": 53,
    "Icon4_2": 79,
    "Icon4_3": 106,
    "Icon4_4": 133,
    "Icon4_5": 160,
    "Icon4_6": 193,
    "Icon4_7": 26,
    "Icon5": 93,
    "Icon6": 120,
    "Icon8": 147,
    "Icon9": 180,
    "IconAccept2": 568,
    "IconAccept3": 610,
    "IconAccept4": 621,
    "IconAccept5": 655,
    "IconAccept6": 686,
    "IconAccept7": 727,
    "IconAccept8": 738,
    "IconAccept9": 343,
    "IconAccept9_1": 384,
    "IconAccept9_2": 395,
    "IconAccept9_3": 429,
    "IconAccept9_4": 460,
    "IconAccept9_5": 501,
    "IconAccept9_6": 522,
    "IconCancel3": 607,
    "IconCancel4": 618,
    "IconCancel5": 652,
    "IconCancel6": 683,
    "IconCancel7": 724,
    "IconCancel8": 735,
    "IconRefresh1_1": 46,
    "IconRefresh1_10": 86,
    "IconRefresh1_11": 113,
    "IconRefresh1_12": 140,
    "IconRefresh1_13": 173,
    "IconRefresh1_14": 200,
    "IconRefresh1_2": 72,
    "IconRefresh1_3": 99,
    "IconRefresh1_4": 126,
    "IconRefresh1_5": 153,
    "IconRefresh1_6": 186,
    "IconRefresh1_7": 19,
    "IconRefresh1_8": 33,
    "IconRefresh1_9": 59,
    "IconSortUpDown1_1": 47,
    "IconSortUpDown1_10": 87,
    "IconSortUpDown1_11": 114,
    "IconSortUpDown1_12": 141,
    "IconSortUpDown1_13": 174,
    "IconSortUpDown1_14": 201,
    "IconSortUpDown1_2": 73,
    "IconSortUpDown1_3": 100,
    "IconSortUpDown1_4": 127,
    "IconSortUpDown1_5": 154,
    "IconSortUpDown1_6": 187,
    "IconSortUpDown1_7": 20,
    "IconSortUpDown1_8": 34,
    "IconSortUpDown1_9": 60,
    "Image1": 5,
    "imie _DataCard1": 689,
    "imie _DataCard2": 288,
    "imie _DataCard3": 463,
    "Imię_DataCard1": 571,
    "Imię_DataCard2": 215,
    "Imię_DataCard5": 346,
    "Label1": 556,
    "Label2": 1,
    "Label3": 7,
    "Label3_1": 767,
    "Label4": 16,
    "Label4_1": 776,
    "Label5_1": 237,
    "Label5_2": 212,
    "Label5_3": 260,
    "Label5_4": 285,
    "Label5_5": 310,
    "Label5_6": 317,
    "Latitiude_DataCard1": 509,
    "Latitiude1": 167,
    "LblAppName1": 557,
    "LblAppName10": 726,
    "LblAppName11": 737,
    "LblAppName2_1": 45,
    "LblAppName2_10": 85,
    "LblAppName2_11": 112,
    "LblAppName2_12": 139,
    "LblAppName2_13": 172,
    "LblAppName2_14": 199,
    "LblAppName2_2": 71,
    "LblAppName2_3": 98,
    "LblAppName2_4": 125,
    "LblAppName2_5": 152,
    "LblAppName2_6": 185,
    "LblAppName2_7": 18,
    "LblAppName2_8": 32,
    "LblAppName2_9": 58,
    "LblAppName4": 342,
    "LblAppName4_1": 383,
    "LblAppName4_2": 394,
    "LblAppName4_3": 428,
    "LblAppName4_4": 459,
    "LblAppName4_5": 500,
    "LblAppName4_6": 521,
    "LblAppName5": 567,
    "LblAppName6": 609,
    "LblAppName7": 620,
    "LblAppName8": 654,
    "LblAppName9": 685,
    "Lokalizacja_DataCard1": 647,
    "Lokalizacja_DataCard2": 730,
    "Lokalizacja_DataCard3": 254,
    "Lokalizacja_DataCard4": 313,
    "Lokalizacja_DataCard5": 421,
    "Lokalizacja_DataCard6": 504,
    "Lokalizacja1": 166,
    "Lokalizacje_usun": 539,
    "Lokalizacje_wyswietl": 553,
    "Lokalizacje_wyswietl_szczegoly": 568,
    "Longitude_DataCard1": 514,
    "Longitude1": 168,
    "MainMenu": 576,
    "Map1": 165,
    "Menedzerowie_usun": 583,
    "Menedzerowie_wyswietl": 597,
    "Menedzerowie_wyswietl_szczegoly": 612,
    "Menedżer_DataCard1": 274,
    "Menedżer_DataCard2": 447,
    "Menedżer_DataCard3": 673,
    "MinuteValue1": 635,
    "MinuteValue2": 409,
    "Nazwa (Title)_DataCard1": 741,
    "Nazwa (Title)_DataCard2": 320,
    "Nazwa (Title)_DataCard3": 525,
    "Nazwa Gatunku_DataCard1": 613,
    "Nazwa Gatunku_DataCard2": 387,
    "Nazwa_DataCard1": 240,
    "nazwisko _DataCard1": 694,
    "nazwisko _DataCard2": 291,
    "nazwisko _DataCard3": 468,
    "Nazwisko_DataCard1": 576,
    "Nazwisko_DataCard2": 218,
    "Nazwisko_DataCard5": 351,
    "NextArrow6_2": 80,
    "NextArrow6_3": 107,
    "NextArrow6_4": 134,
    "NextArrow6_5": 161,
    "NextArrow6_6": 194,
    "NextArrow6_7": 27,
    "Numer telefonu_DataCard1": 586,
    "Numer telefonu_DataCard2": 224,
    "Numer telefonu_DataCard5": 361,
    "numer_telefonu_DataCard1": 699,
    "numer_telefonu_DataCard2": 294,
    "numer_telefonu_DataCard3": 473,
    "Oceny użytkownika_DataCard1": 337,
    "Oceny użytkownika_DataCard2": 550,
    "Ograniczenie wiekowe_DataCard1": 751,
    "Ograniczenie wiekowe_DataCard2": 326,
    "Ograniczenie wiekowe_DataCard3": 535,
    "Opis zadania_DataCard1": 263,
    "Opis zadania_DataCard2": 432,
    "Opis zadania_DataCard3": 658,
    "Opis_DataCard1": 637,
    "Opis_DataCard2": 411,
    "Pracownicy_usun": 638,
    "Pracownicy_wyswietl": 652,
    "Pracownicy_wyswietl_szczegoly": 667,
    "Pracownik_DataCard1": 269,
    "Pracownik_DataCard2": 442,
    "Pracownik_DataCard3": 668,
    "Rectangle12_1": 56,
    "Rectangle12_10": 96,
    "Rectangle12_11": 123,
    "Rectangle12_12": 150,
    "Rectangle12_13": 183,
    "Rectangle12_14": 210,
    "Rectangle12_2": 83,
    "Rectangle12_3": 110,
    "Rectangle12_4": 137,
    "Rectangle12_5": 164,
    "Rectangle12_6": 197,
    "Rectangle12_7": 30,
    "Rectangle12_8": 43,
    "Rectangle12_9": 69,
    "RectQuickActionBar4": 341,
    "RectQuickActionBar4_1": 382,
    "RectQuickActionBar4_2": 393,
    "RectQuickActionBar4_3": 427,
    "RectQuickActionBar4_4": 458,
    "RectQuickActionBar4_5": 499,
    "RectQuickActionBar4_6": 520,
    "RectQuickActionBar5_1": 0,
    "RectQuickActionBar5_10": 184,
    "RectQuickActionBar5_11": 236,
    "RectQuickActionBar5_12": 17,
    "RectQuickActionBar5_13": 211,
    "RectQuickActionBar5_14": 259,
    "RectQuickActionBar5_15": 284,
    "RectQuickActionBar5_16": 309,
    "RectQuickActionBar5_17": 316,
    "RectQuickActionBar5_18": 340,
    "RectQuickActionBar5_19": 381,
    "RectQuickActionBar5_2": 6,
    "RectQuickActionBar5_20": 392,
    "RectQuickActionBar5_21": 426,
    "RectQuickActionBar5_22": 457,
    "RectQuickActionBar5_23": 498,
    "RectQuickActionBar5_24": 519,
    "RectQuickActionBar5_25": 555,
    "RectQuickActionBar5_26": 566,
    "RectQuickActionBar5_27": 606,
    "RectQuickActionBar5_28": 619,
    "RectQuickActionBar5_29": 653,
    "RectQuickActionBar5_3": 766,
    "RectQuickActionBar5_30": 684,
    "RectQuickActionBar5_31": 725,
    "RectQuickActionBar5_32": 736,
    "RectQuickActionBar5_33": 31,
    "RectQuickActionBar5_34": 57,
    "RectQuickActionBar5_35": 84,
    "RectQuickActionBar5_36": 111,
    "RectQuickActionBar5_37": 138,
    "RectQuickActionBar5_38": 171,
    "RectQuickActionBar5_39": 198,
    "RectQuickActionBar5_5": 44,
    "RectQuickActionBar5_6": 70,
    "RectQuickActionBar5_7": 97,
    "RectQuickActionBar5_8": 124,
    "RectQuickActionBar5_9": 151,
    "RectQuickActionBar6": 608,
    "Rola _DataCard1": 581,
    "Rola _DataCard2": 221,
    "Rola _DataCard5": 356,
    "SearchIcon1_1": 50,
    "SearchIcon1_10": 90,
    "SearchIcon1_11": 117,
    "SearchIcon1_12": 144,
    "SearchIcon1_13": 177,
    "SearchIcon1_14": 204,
    "SearchIcon1_2": 76,
    "SearchIcon1_3": 103,
    "SearchIcon1_4": 130,
    "SearchIcon1_5": 157,
    "SearchIcon1_6": 190,
    "SearchIcon1_7": 23,
    "SearchIcon1_8": 37,
    "SearchIcon1_9": 63,
    "Separator1": 408,
    "Separator3": 634,
    "Separator7_1": 55,
    "Separator7_10": 95,
    "Separator7_11": 122,
    "Separator7_12": 149,
    "Separator7_13": 182,
    "Separator7_14": 209,
    "Separator7_2": 82,
    "Separator7_3": 109,
    "Separator7_4": 136,
    "Separator7_5": 163,
    "Separator7_6": 196,
    "Separator7_7": 29,
    "Separator7_8": 42,
    "Separator7_9": 68,
    "Spotkania_usun": 693,
    "Spotkania_wyswietl": 707,
    "Spotkania_wyswietl_szczegoly": 722,
    "StarVisible1": 250,
    "StarVisible10": 572,
    "StarVisible11": 577,
    "StarVisible12": 597,
    "StarVisible13": 602,
    "StarVisible14": 582,
    "StarVisible15": 592,
    "StarVisible16": 587,
    "StarVisible17": 347,
    "StarVisible18": 614,
    "StarVisible19": 352,
    "StarVisible2": 255,
    "StarVisible20": 625,
    "StarVisible21": 630,
    "StarVisible22": 638,
    "StarVisible23": 643,
    "StarVisible24": 648,
    "StarVisible25": 362,
    "StarVisible26": 659,
    "StarVisible27": 664,
    "StarVisible28": 669,
    "StarVisible29": 674,
    "StarVisible3": 270,
    "StarVisible30": 679,
    "StarVisible31": 357,
    "StarVisible32": 690,
    "StarVisible33": 695,
    "StarVisible34": 700,
    "StarVisible35": 705,
    "StarVisible36": 710,
    "StarVisible37": 715,
    "StarVisible38": 720,
    "StarVisible39": 388,
    "StarVisible4": 275,
    "StarVisible40": 731,
    "StarVisible41": 510,
    "StarVisible42": 742,
    "StarVisible43": 747,
    "StarVisible44": 752,
    "StarVisible45": 757,
    "StarVisible46": 762,
    "StarVisible47": 399,
    "StarVisible48": 404,
    "StarVisible49": 412,
    "StarVisible5": 280,
    "StarVisible50": 417,
    "StarVisible51": 422,
    "StarVisible52": 515,
    "StarVisible53": 433,
    "StarVisible54": 438,
    "StarVisible55": 443,
    "StarVisible56": 448,
    "StarVisible57": 453,
    "StarVisible59": 464,
    "StarVisible6": 333,
    "StarVisible60": 469,
    "StarVisible61": 474,
    "StarVisible62": 479,
    "StarVisible63": 484,
    "StarVisible64": 489,
    "StarVisible65": 494,
    "StarVisible67": 505,
    "StarVisible69": 526,
    "StarVisible7": 377,
    "StarVisible70": 531,
    "StarVisible71": 536,
    "StarVisible72": 541,
    "StarVisible73": 546,
    "StarVisible75": 551,
    "StarVisible8": 367,
    "StarVisible9": 372,
    "Termin wykonania_DataCard1": 266,
    "Termin wykonania_DataCard2": 437,
    "Termin wykonania_DataCard3": 663,
    "TextSearchBox1_1": 49,
    "TextSearchBox1_10": 89,
    "TextSearchBox1_11": 116,
    "TextSearchBox1_12": 143,
    "TextSearchBox1_13": 176,
    "TextSearchBox1_14": 203,
    "TextSearchBox1_2": 75,
    "TextSearchBox1_3": 102,
    "TextSearchBox1_4": 129,
    "TextSearchBox1_5": 156,
    "TextSearchBox1_6": 189,
    "TextSearchBox1_7": 22,
    "TextSearchBox1_8": 36,
    "TextSearchBox1_9": 62,
    "Title6_1": 54,
    "Title6_10": 94,
    "Title6_11": 121,
    "Title6_12": 148,
    "Title6_13": 181,
    "Title6_14": 208,
    "Title6_2": 81,
    "Title6_3": 108,
    "Title6_4": 135,
    "Title6_5": 162,
    "Title6_6": 195,
    "Title6_7": 28,
    "Title6_8": 41,
    "Title6_9": 67,
    "Toggle_satelite": 170,
    "wynagrodzenie _DataCard1": 719,
    "wynagrodzenie _DataCard2": 306,
    "wynagrodzenie _DataCard3": 493,
    "Wynagrodzenie_DataCard1": 601,
    "Wynagrodzenie_DataCard2": 233,
    "Wynagrodzenie_DataCard3": 376,
    "Zadania_usun": 746,
    "Zadania_wyswietl": 760,
    "Zadania_wyswietl_szczegoly": 775,
    "Załączniki1": 169
  },
  "ResourcesJsonIndices": {
    "Image-Filmoplaner": 1,
    "Image-filmoplanerbackground": 2,
    "Image-SampleImage": 0
  },
  "RuleScreenIdWithoutScreen": {},
  "TemplateVersions": {},
  "VolatileProperties": {
    "AnalysisLoadTime": 5.9141401,
    "ControlCount": {
      "button": 24,
      "combobox": 18,
      "datepicker": 16,
      "dropdown": 4,
      "form": 14,
      "formViewer": 6,
      "gallery": 14,
      "galleryTemplate": 14,
      "icon": 119,
      "image": 1,
      "label": 314,
      "rectangle": 74,
      "screen": 38,
      "text": 49,
      "typedDataCard": 94
    },
    "DeserializationLoadTime": 12.4911853,
    "ErrorCount": 0
  },
  "WasLocalDatabaseReferencesEmpty": true
}